lxg/__init__.py
lxg/loggable.py
lxg/version.py
tests/__init__.py
tests/loggable_test.py
lxg-0.1.1rc1.dist-info/LICENSE
lxg-0.1.1rc1.dist-info/METADATA
lxg-0.1.1rc1.dist-info/WHEEL
lxg-0.1.1rc1.dist-info/top_level.txt
lxg-0.1.1rc1.dist-info/RECORD
